innerhtml/Constants.py
innerhtml/Core.py
innerhtml/Types.py
innerhtml/__init__.py
innerhtml-0.0.1.dist-info/METADATA
innerhtml-0.0.1.dist-info/WHEEL
innerhtml-0.0.1.dist-info/top_level.txt
innerhtml-0.0.1.dist-info/RECORD
