Metadata-Version: 2.1
Name: innerhtml
Version: 0.0.1
Summary: HTML for humans.
Home-page: https://github.com/ArticOff/innerhtml
Author: Artic#3065
Author-email: artic.admisoffi@gmail.com
Maintainer: Artic#3065
Maintainer-email: artic.admisoffi@gmail.com
License: MIT
Project-URL: Source, https://github.com/ArticOff/innerhtml
Project-URL: Discord, https://articoff.github.io/discord
Project-URL: Tracker, https://github.com/ArticOff/innerhtml/issues
Platform: UNKNOWN
Classifier: Development Status :: 5 - Production/Stable
Classifier: License :: OSI Approved :: MIT License
Classifier: Intended Audience :: Developers
Classifier: Natural Language :: English
Classifier: Programming Language :: Python :: 3
Classifier: Programming Language :: Python
